LoggerX/__init__.py
LoggerX/config.py
LoggerX/handlers.py
LoggerX-0.2.dist-info/LICENSE
LoggerX-0.2.dist-info/METADATA
LoggerX-0.2.dist-info/WHEEL
LoggerX-0.2.dist-info/top_level.txt
LoggerX-0.2.dist-info/RECORD
