Metadata-Version: 2.1
Name: LoggerX
Version: 0.2
Summary: 自定义日志模块
Home-page: https://github.com/al6nlee/LoggerX
Author: alan
Author-email: al6nlee@gmail.com
License: Apache-2.0
Platform: UNKNOWN
Classifier: Intended Audience :: Developers
Classifier: License :: OSI Approved :: Apache Software License
Classifier: Programming Language :: Python
Classifier: Programming Language :: Python :: 3.6
Classifier: Programming Language :: Python :: 3.7
Classifier: Programming Language :: Python :: 3.8
Classifier: Topic :: Software Development
Requires-Python: >=3.6
License-File: LICENSE
